{"is_source_file": true, "format": "Python", "description": "ASGI configuration file for a Django project that exposes the ASGI callable.", "external_files": ["config/settings.py"], "external_methods": ["django.core.asgi.get_asgi_application"], "published": ["application"], "classes": [], "methods": [], "calls": ["django.core.asgi.get_asgi_application()"], "search-terms": ["ASGI", "Django", "application", "asgi.py"], "state": 2, "file_id": 17, "knowledge_revision": 34, "git_revision": "42b286867fdff3844bb6c20c26f1579d1e130952", "ctags": [{"_type": "tag", "name": "application", "path": "/tmp/kavia/workspace/code-generation/tic-tac-toe-game-291-300/tic_tac_toe_backend/config/asgi.py", "pattern": "/^application = get_asgi_application()$/", "language": "Python", "kind": "variable"}], "hash": "63d5777b090ac063ecd29c3dfa786ba5", "format-version": 4, "code-base-name": "tic_tac_toe_backend", "filename": "tic_tac_toe_backend/config/asgi.py", "fields": [{"name": "application = get_asgi_application()", "scope": "", "scopeKind": "", "description": "unavailable"}], "revision_history": [{"34": "42b286867fdff3844bb6c20c26f1579d1e130952"}]}